rfcat-2.0.1.data/scripts/rfcat
rfcat-2.0.1.data/scripts/rfcat_bootloader
rfcat-2.0.1.data/scripts/rfcat_msfrelay
rfcat-2.0.1.data/scripts/rfcat_server
rflib/__init__.py
rflib/bits.py
rflib/cc111Xhparser.py
rflib/ccrecvdump.py
rflib/ccspecan.py
rflib/chipcon_nic.py
rflib/chipcon_usb.py
rflib/chipcondefs.py
rflib/const.py
rflib/fakedongle_nic.py
rflib/intelhex.py
rflib/rflib_defs.py
rflib/rflib_version.py
rflib/vstruct/__init__.py
rflib/vstruct/builder.py
rflib/vstruct/primitives.py
rflib/vstruct/defs/__init__.py
rflib/vstruct/defs/elf.py
rflib/vstruct/defs/kdcom.py
rflib/vstruct/defs/pe.py
rflib/vstruct/defs/win32.py
rflib/vstruct/defs/macho/__init__.py
rflib/vstruct/defs/macho/const.py
rflib/vstruct/defs/macho/fat.py
rflib/vstruct/defs/macho/loader.py
tests/__init__.py
tests/test_api.py
tests/test_basics.py
tests/test_bits.py
vstruct/__init__.py
vstruct/builder.py
vstruct/primitives.py
vstruct/defs/__init__.py
vstruct/defs/elf.py
vstruct/defs/kdcom.py
vstruct/defs/pe.py
vstruct/defs/win32.py
vstruct/defs/macho/__init__.py
vstruct/defs/macho/const.py
vstruct/defs/macho/fat.py
vstruct/defs/macho/loader.py
rfcat-2.0.1.dist-info/LICENSE
rfcat-2.0.1.dist-info/LICENSE.CC-Bootloader
rfcat-2.0.1.dist-info/METADATA
rfcat-2.0.1.dist-info/WHEEL
rfcat-2.0.1.dist-info/top_level.txt
rfcat-2.0.1.dist-info/RECORD
