Metadata-Version: 2.1
Name: rfcat
Version: 2.0.1
Summary: the swiss army knife of subGHz
Home-page: https://github.com/atlas0fd00m/rfcat
Author: atlas of d00m
Author-email: atlas@r4780y.com
License: UNKNOWN
Download-URL: https://github.com/atlas0fd00m/rfcat/archive/v1.9.1.tar.gz
Keywords: radio,subghz,cc1111,chipcon,hacking,reverse engineering
Platform: UNKNOWN
Classifier: Development Status :: 5 - Production/Stable
Classifier: Intended Audience :: Telecommunications Industry
Classifier: Topic :: Communications
Classifier: License :: OSI Approved :: BSD License
Classifier: Programming Language :: Python :: 2
Classifier: Programming Language :: Python :: 2.7
Classifier: Programming Language :: Python :: 3
Classifier: Programming Language :: Python :: 3.8
Requires-Python: >=2.7
Provides-Extra: specan
License-File: LICENSE
License-File: LICENSE.CC-Bootloader
